diq
