Metadata-Version: 2.1
Name: diq
Version: 0.1.0
Summary: Pythonic Object Serializer
Home-page: https://github.com/Jyonn/dik
Author: Qijiong Liu
Author-email: liu@qijiong.work
License: MIT Licence
Keywords: dict,class
Platform: any
License-File: LICENSE
